pysterling/__init__.py
pysterling/archaic.py
pysterling/sterling.py
pysterling/sterling.pyi
pysterling/vat.py
pysterling-1.0.0.dist-info/LICENSE.txt
pysterling-1.0.0.dist-info/METADATA
pysterling-1.0.0.dist-info/WHEEL
pysterling-1.0.0.dist-info/top_level.txt
pysterling-1.0.0.dist-info/RECORD
